LICENSE
README.md
setup.cfg
setup.py
src/sensestreet/__init__.py
src/sensestreet/anonymise.py
src/sensestreet/auth_header_builder.py
src/sensestreet/deterministic_anonymization.py
src/sensestreet/sensestreet_client.py
src/sensestreet.egg-info/PKG-INFO
src/sensestreet.egg-info/SOURCES.txt
src/sensestreet.egg-info/dependency_links.txt
src/sensestreet.egg-info/requires.txt
src/sensestreet.egg-info/top_level.txt
src/sensestreet/data/__init__.py
src/sensestreet/data/unique_first_names.py
src/sensestreet/data/unique_last_names.py