Metadata-Version: 2.4
Name: sensestreet
Version: 1.0.16
Home-page: https://sensestreet.com
Author: Sense Street
Author-email: engineering@sensestreet.com
License: Apache
License-File: LICENSE
Requires-Dist: requests
Requires-Dist: Authlib
Requires-Dist: cryptography
Requires-Dist: lxml
Dynamic: author
Dynamic: author-email
Dynamic: description
Dynamic: description-content-type
Dynamic: home-page
Dynamic: license
Dynamic: license-file
Dynamic: requires-dist
